vseed/__init__.py
vseed/virdow.py
vseed/vseed.py
vseed-1.0.1.dist-info/LICENSE
vseed-1.0.1.dist-info/METADATA
vseed-1.0.1.dist-info/WHEEL
vseed-1.0.1.dist-info/top_level.txt
vseed-1.0.1.dist-info/RECORD
