Metadata-Version: 2.1
Name: vseed
Version: 1.0.1
Summary: A virus seed dedicated to learning to make computer viruses(virus seed)
Home-page: https://pypi.org/manage/projects/
Author: BeAbledKote
Author-email: 1808873428@qq.com
Maintainer: BeAbledKote
Maintainer-email: 1808873428@qq.com
License: Public domain
Platform: any
License-File: LICENSE
